hkopenai/hk_climate_mcp_server/__init__.py
hkopenai/hk_climate_mcp_server/__main__.py
hkopenai/hk_climate_mcp_server/server.py
hkopenai/hk_climate_mcp_server/tools/astronomical.py
hkopenai/hk_climate_mcp_server/tools/current_weather.py
hkopenai/hk_climate_mcp_server/tools/forecast.py
hkopenai/hk_climate_mcp_server/tools/lightning.py
hkopenai/hk_climate_mcp_server/tools/radiation.py
hkopenai/hk_climate_mcp_server/tools/temperature.py
hkopenai/hk_climate_mcp_server/tools/tides.py
hkopenai/hk_climate_mcp_server/tools/visibility.py
hkopenai/hk_climate_mcp_server/tools/warnings.py
hkopenai_hk_climate_mcp_server-0.4.1.dist-info/licenses/LICENSE
hkopenai_hk_climate_mcp_server-0.4.1.dist-info/METADATA
hkopenai_hk_climate_mcp_server-0.4.1.dist-info/WHEEL
hkopenai_hk_climate_mcp_server-0.4.1.dist-info/entry_points.txt
hkopenai_hk_climate_mcp_server-0.4.1.dist-info/top_level.txt
hkopenai_hk_climate_mcp_server-0.4.1.dist-info/RECORD
